<?xml version="1.0" encoding="UTF-8"?>
<objects serializationModel="Studio.02.02.00">
	<object class="AudioFile" id="{8eb0518f-f769-4412-994b-d535ab707778}">
		<property name="assetPath">
			<value>tanks/weapon/cannons/cannon_reloading/swed_centurion_mk10/reloading_close_heavy_exterior-005.wav</value>
		</property>
		<property name="frequencyInKHz">
			<value>44.0999985</value>
		</property>
		<property name="channelCount">
			<value>2</value>
		</property>
		<property name="length">
			<value>2.266734693877551</value>
		</property>
		<relationship name="masterAssetFolder">
			<destination>{0bf82b67-a3f1-4871-b0e3-529071fffc30}</destination>
		</relationship>
	</object>
</objects>
